gvanim/__init__.py
gvanim/__main__.py
gvanim/action.py
gvanim/animation.py
gvanim/jupyter.py
gvanim/render.py
GraphvizAnim-1.1.0.dist-info/LICENSE.txt
GraphvizAnim-1.1.0.dist-info/METADATA
GraphvizAnim-1.1.0.dist-info/WHEEL
GraphvizAnim-1.1.0.dist-info/top_level.txt
GraphvizAnim-1.1.0.dist-info/RECORD
