Metadata-Version: 2.1
Name: GraphvizAnim
Version: 1.1.0
Summary: A tool to create animated graph visualizations, based on graphviz
Home-page: https://github.com/mapio/GraphvizAnim
Author: Massimo Santini
Author-email: santini@di.unimi.it
License: GNU/GPLv3
Keywords: drawing graph animation
Platform: UNKNOWN
Classifier: Development Status :: 5 - Production/Stable
Classifier: License :: OSI Approved :: GNU General Public License v3 or later (GPLv3+)
Classifier: Operating System :: Unix
Classifier: Topic :: Software Development :: Libraries :: Python Modules
